MANIFEST.in
README.md
setup.py
lcyframe/__init__.py
lcyframe/__main__.py
lcyframe/app.py
lcyframe/base.py
lcyframe/beanstalk_server.py
lcyframe/celery_server.py
lcyframe/crontab_server.py
lcyframe/mq_server.py
lcyframe/mqtt_server.py
lcyframe/nsq_server.py
lcyframe/websocket_server.py
lcyframe.egg-info/PKG-INFO
lcyframe.egg-info/SOURCES.txt
lcyframe.egg-info/dependency_links.txt
lcyframe.egg-info/entry_points.txt
lcyframe.egg-info/not-zip-safe
lcyframe.egg-info/requires.txt
lcyframe.egg-info/top_level.txt
lcyframe/demo/.gitignore
lcyframe/demo/README2.pdf
lcyframe/demo/app_start.py
lcyframe/demo/base.py
lcyframe/demo/beanstalk_start.py
lcyframe/demo/celery_start.py
lcyframe/demo/connection_wechat.py
lcyframe/demo/crontab_start.py
lcyframe/demo/helper.py
lcyframe/demo/keys.py
lcyframe/demo/mq_start.py
lcyframe/demo/mqtt_start.py
lcyframe/demo/nsq_start.py
lcyframe/demo/requirements.txt
lcyframe/demo/socket_start.py
lcyframe/demo/websocket_start.py
lcyframe/demo/.idea/.gitignore
lcyframe/demo/.idea/demo.iml
lcyframe/demo/.idea/modules.xml
lcyframe/demo/.idea/vcs.xml
lcyframe/demo/.idea/workspace.xml
lcyframe/demo/.idea/inspectionProfiles/profiles_settings.xml
lcyframe/demo/SDK/__init__.py
lcyframe/demo/SDK/alipay_openapi.py
lcyframe/demo/SDK/minio_xa/__init__.py
lcyframe/demo/SDK/minio_xa/minio_storage.py
lcyframe/demo/api_schema/admin.yml
lcyframe/demo/api_schema/basics.yml
lcyframe/demo/api_schema/demo.yml
lcyframe/demo/api_schema/permission.yml
lcyframe/demo/api_schema/upload.yml
lcyframe/demo/api_schema/websocket.yml
lcyframe/demo/api_schema/basics/upload.yml
lcyframe/demo/api_schema/user/user.yml
lcyframe/demo/context/__init__.py
lcyframe/demo/context/celeryconfig.py
lcyframe/demo/context/example.yml
lcyframe/demo/context/localhost.yml
lcyframe/demo/docker/docker-compose.yml
lcyframe/demo/handler/__init__.py
lcyframe/demo/handler/admin_handler.py
lcyframe/demo/handler/basics_handler.py
lcyframe/demo/handler/demo_handler.py
lcyframe/demo/handler/permission_handler.py
lcyframe/demo/handler/upload_handler.py
lcyframe/demo/handler/user_handler.py
lcyframe/demo/handler/websocket_handler.py
lcyframe/demo/model/__init__.py
lcyframe/demo/model/admin_model.py
