Metadata-Version: 2.1
Name: lcyframe
Version: 3.8.3
Summary: A Fast ApiServer Frame for python3
Home-page: 
Author: lcylln
Author-email: 123220663@qq.com
Keywords: lcyframe
Platform: any
